HISTORY.md
LICENSE.txt
MANIFEST.in
README.md
setup.py
ka_drf_utils.egg-info/PKG-INFO
ka_drf_utils.egg-info/SOURCES.txt
ka_drf_utils.egg-info/dependency_links.txt
ka_drf_utils.egg-info/requires.txt
ka_drf_utils.egg-info/top_level.txt
kitchenart/__init__.py
kitchenart/drf.py
kitchenart/helpers.py
kitchenart/models.py
kitchenart/pagination.py
kitchenart/signaling.py
kitchenart/log/__init__.py
kitchenart/log/publisher.py
kitchenart/log/receivers.py
kitchenart/log/signal.py
kitchenart/log/views.py
kitchenart/utils/__init__.py
kitchenart/utils/broker.py