Metadata-Version: 2.1
Name: ka-drf-utils
Version: 0.5.0
Summary: KitchenArt utility package
Home-page: UNKNOWN
Author: MSJ Development Team
Author-email: engineering@muliasuksesjaya.com
License: MIT
Platform: UNKNOWN
Classifier: Development Status :: 4 - Beta
Classifier: Framework :: Django
Classifier: Intended Audience :: Developers
Classifier: Natural Language :: English
Classifier: License :: OSI Approved :: Apache Software License
Classifier: Operating System :: OS Independent
Classifier: Programming Language :: Python :: 3.6
Classifier: Programming Language :: Python :: 3.8
Classifier: Topic :: Software Development :: Libraries :: Python Modules
Provides-Extra: broker
